{
	"selectList": [
		{"type": "story", "id":  101, "icon":  1},
		{"type": "stage", "id":  101, "icon":  1, "mark":  1},
		{"type": "stage", "id":  201, "icon":  2, "mark":  2},
		{"type": "stage", "id":  301, "icon":  3, "mark":  3},
		{"type": "story", "id":  201, "icon":  2},
		{"type": "stage", "id":  401, "icon":  4, "mark":  4},
		{"type": "stage", "id":  501, "icon":  5, "mark":  5},
		{"type": "stage", "id":  601, "icon":  6, "mark":  6},
		{"type": "stage", "id":  701, "icon":  7, "mark":  7},
		{"type": "stage", "id":  801, "icon":  8, "mark":  8},
		{"type": "stage", "id":  901, "icon":  9, "mark":  9},
		{"type": "story", "id":  301, "icon":  3},
		{"type": "stage", "id": 1001, "icon": 10, "mark": 10},
		{"type": "stage", "id": 1101, "icon": 11, "mark": 11},
		{"type": "stage", "id": 1201, "icon": 12, "mark": 12},
		{"type": "stage", "id": 1301, "icon": 13, "mark": 13},
		{"type": "stage", "id": 1401, "icon": 14, "mark": 14},
		{"type": "stage", "id": 1501, "icon": 15, "mark": 15},
		{"type": "stage", "id": 1601, "icon": 16, "mark": 16},
		{"type": "stage", "id": 1701, "icon": 17, "mark": 17},
		{"type": "stage", "id": 1801, "icon": 18, "mark": 18},
		{"type": "story", "id":  401, "icon":  4},
		{"type": "stage", "id": 1901, "icon": 19, "mark": 19},
		{"type": "stage", "id": 2001, "icon": 20, "mark": 20},
		{"type": "stage", "id": 2101, "icon": 21, "mark": 21},
		{"type": "stage", "id": 2201, "icon": 22, "mark": 22},
		{"type": "stage", "id": 2301, "icon": 23, "mark": 23},
		{"type": "stage", "id": 2401, "icon": 24, "mark": 24},
		{"type": "stage", "id": 2501, "icon": 25, "mark": 25},
		{"type": "stage", "id": 2601, "icon": 26, "mark": 26},
		{"type": "stage", "id": 2701, "icon": 27, "mark": 27},
		{"type": "story", "id":  501, "icon":  5}
	],
	"puppetList": [
		{"kind": "guru", "openStar":  1},
		{"kind": "kuma", "openStar":  5},
		{"kind": "ribb", "openStar": 15},
		{"kind": "pebu", "openStar": 30},
		{"kind": "mami", "openStar": 45},
		{"kind": "hand", "openStar": 55},
		{"kind": "bear", "openStar": 65},
		{"kind": "guda", "openStar": 70},
		{"kind": "robo", "openStar": 75}
	],
}
